indexbinder/__init__.py
indexbinder/image_search.py
indexbinder/indexing.py
indexbinder-0.1.2.dist-info/METADATA
indexbinder-0.1.2.dist-info/WHEEL
indexbinder-0.1.2.dist-info/top_level.txt
indexbinder-0.1.2.dist-info/RECORD
