Metadata-Version: 2.1
Name: indexbinder
Version: 0.1.2
Summary: A library for storing and managing FAISS indexes on Google Cloud Storage. Fashionably serverless.
Author-email: jibx <bounces@example.com>
Project-URL: Homepage, https://github.com/jibsx/indexbinder
Project-URL: Bug Tracker, https://github.com/jibsx/indexbinder/issues
Classifier: Programming Language :: Python :: 3
Classifier: License :: OSI Approved :: MIT License
Classifier: Operating System :: OS Independent
Requires-Python: >=3.7
Requires-Dist: google-cloud-storage
Requires-Dist: torch
Requires-Dist: transformers
Requires-Dist: faiss-cpu
Requires-Dist: numpy
Requires-Dist: Pillow
Requires-Dist: huggingface-hub
Requires-Dist: SentencePiece
Provides-Extra: dev
Requires-Dist: pytest ; extra == 'dev'
Requires-Dist: pytest-mock ; extra == 'dev'
